{
     "settings":
    {
        "calibration_settings": {
            "start_configuration": [0.7987529296875, 0.6302978515625, -1.84855859375, 0.798107421875, 2.3330693359375, -0.2563291015625, -1.5373125],
            "calibration_pose":
            {
                "position": [1.0896, -0.04371, -0.15091],
                "orientation": [0.93665, 0.00855181, 0.349031, 0.0285096]
            }
        },
        "recording_settings": {
            "sampling_rate": 50,
            "constraint_trigger_mechanism": "web_trigger"
        },
        "labeling_settings": {
            "divisor": 50,
            "window": 50
        },
        "modeling_settings": {
            "planner": "RRTkConfigDefault",
            "bandwidth": 0.075,
            "number_of_samples": 25,
            "cull_overconstrained": false,
            "automate_culling_threshold": true,
            "culling_threshold": 5
        },
        "raw_output_directory": "./raw_demonstrations/",
        "labeled_output_directory": "./labeled_demonstrations/"

    },
    "constraints": [
        {
            "class": "PlanarConstraint",
            "init_args":
            {
                "constraint_id": 1,
                "item_id": 1,
                "reference_position": 0.03174696254091882,
                "threshold_distance": 0.00,
                "direction": "negative",
                "axis": "z"
            }
        },
        {
            "class": "PlanarConstraint",
            "init_args":
            {
                "constraint_id": 2,
                "item_id": 1,
                "reference_position": -0.0605552,
                "threshold_distance": 0.00,
                "direction": "positive",
                "axis": "z"
            }
        },
        {
            "class": "OrientationConstraint",
            "init_args" :
                {
                    "constraint_id": 3,
                    "item_id": 1,
                    "threshold_angle": 8,
                    "reference_orientation": [0.017721236427960724, -0.6896867930096543, 0.723890701324838, 0.0005812598018143569],
                    "axis": "z"
                }
        },
                {
            "class": "OrientationConstraint",
            "init_args" :
                {
                    "constraint_id": 4,
                    "item_id": 1,
                    "threshold_angle": 15,
                    "reference_orientation": [-0.5025809059472035, -0.455533381558173, 0.5438250996747817, -0.4941214751730367],
                    "axis": "z"
                }
        },
         {
            "class": "OverUnderConstraint",
            "init_args" :
                {
                    "constraint_id": 5,
                    "above_item_id": 1,
                    "below_item_id": 2,
                    "threshold_distance": 0.08,
                    "reference_pose": {
                        "position": [0.6109314212320098, 0.36505230607231814, -0.11699769749427],
                        "orientation":  [-0.003588055934499179, -0.9989722612831933, -0.004546341379431041, 0.044954174682852586]
                    },
                    "axis": "y"
                }
        },
         {
            "class": "OverUnderConstraint",
            "init_args" :
                {
                    "constraint_id": 6,
                    "above_item_id": 1,
                    "below_item_id": 2,
                    "threshold_distance": 0.08,
                    "reference_pose": {
                        "position": [0.6704478539344562, -0.5229082037023104, 0.19256496442827226],
                        "orientation":  [0.006374615488541097, 0.9999187409979692, -0.0053489284453452565, 0.009657362108587664]
                    },
                    "axis": "y"
                }
        }
    ],
    "triggers": [
        {
            "class": "WebTrigger",
            "init_args":
            {
                "constraint_id": 1
            }
        },
        {
            "class": "WebTrigger",
            "init_args":
            {
                "constraint_id": 2
            }
        },
        {
            "class": "WebTrigger",
            "init_args":
            {
                "constraint_id": 3
            }
        },
        {
            "class": "WebTrigger",
            "init_args":
            {
                "constraint_id": 4
            }
        },
         {
            "class": "WebTrigger",
            "init_args":
            {
                "constraint_id": 5
            }
        },
        {
            "class": "WebTrigger",
            "init_args":
            {
                "constraint_id": 6
            }
        }
    ],
    "items": [],
    "robots": [
        {
            "class": "SawyerRobot",
            "init_args":
            {
                "item_id": 1,
                "reference_pose":
                {
                    "position": [0.578695253097807, -0.39773819035311436, -0.011090908106854147],
                    "orientation":[-0.7071318608127011, -0.02090705254793435, -0.011310713675474933, -0.7066820319871432]

                }
            }
        }

    ]

}
